synapse_admin/__init__.py
synapse_admin/__main__.py
synapse_admin/base.py
synapse_admin/client.py
synapse_admin/management.py
synapse_admin/media.py
synapse_admin/room.py
synapse_admin/user.py
matrix_synapse_admin-0.7.0.dist-info/LICENSE
matrix_synapse_admin-0.7.0.dist-info/METADATA
matrix_synapse_admin-0.7.0.dist-info/WHEEL
matrix_synapse_admin-0.7.0.dist-info/top_level.txt
matrix_synapse_admin-0.7.0.dist-info/RECORD
