Metadata-Version: 2.1
Name: matrix-synapse-admin
Version: 0.7.0
Summary: A Python wrapper for Matrix Synapse admin API
Home-page: https://github.com/KnugiHK/synapse-admin-api-python
Author: KnugiHK
Author-email: info@knugi.com
License: UNKNOWN
Platform: UNKNOWN
Classifier: Programming Language :: Python :: 3 :: Only
Classifier: Programming Language :: Python :: 3.7
Classifier: Programming Language :: Python :: 3.8
Classifier: Programming Language :: Python :: 3.9
Classifier: Programming Language :: Python :: 3.10
Classifier: License :: OSI Approved :: MIT License
Classifier: Operating System :: OS Independent
Classifier: Development Status :: 4 - Beta
Classifier: Topic :: Communications :: Chat
Classifier: Topic :: Utilities
Classifier: Intended Audience :: Developers
Classifier: Intended Audience :: System Administrators
Requires-Python: >=3.7
License-File: LICENSE
Requires-Dist: httpx (>=0.21.1)
